activemq_api_client/__init__.py
activemq_api_client/client.py
activemq_api_client/connector.py
unit_tests/__init__.py
unit_tests/test_activemq_client.py
activemq_api_client-0.0.4.dist-info/LICENSE
activemq_api_client-0.0.4.dist-info/METADATA
activemq_api_client-0.0.4.dist-info/WHEEL
activemq_api_client-0.0.4.dist-info/top_level.txt
activemq_api_client-0.0.4.dist-info/RECORD
