Metadata-Version: 2.1
Name: activemq-api-client
Version: 0.0.4
Summary: A Python client for ActiveMQ REST API
Home-page: https://github.com/TonySchneider/activemq-api-client
Author: Tony Schneider
Author-email: tonysch05@gmail.com
License: MIT
Keywords: activemq api client
Platform: UNKNOWN
Requires-Dist: requests ==2.31.0
Requires-Dist: pytest ~=7.2.0
Requires-Dist: setuptools ~=59.6.0
